hyperetes/__init__.py
hyperetes/assistant.py
hyperetes-0.0.1.dist-info/LICENSE
hyperetes-0.0.1.dist-info/METADATA
hyperetes-0.0.1.dist-info/WHEEL
hyperetes-0.0.1.dist-info/top_level.txt
hyperetes-0.0.1.dist-info/RECORD
